{"name":"Jeesite","tagline":"企业信息管理系统基础框架","body":"#JeeSite 企业信息管理系统基础框架\r\n=======\r\n\r\n##框架简介\r\n\r\nJeeSite是一个 **开源的企业信息管理系统** 基础框架。主要定位于“企业信息管理”领域，可用作企业信息管理类系统、网站后台管理类系统等。JeeSite是非常强调开发的高效性、健壮性和安全性的。\r\n\r\nJeeSite是轻量级的，简单易学，本框架以Spring Framework为核心、Spring MVC作为模型视图控制器、Spring Data JPA + Hibernate作为数据库操作层，此组合是Java界业内最经典、最优的搭配组合。前端界面风格采用了结构简单、性能优良、页面精致的Twitter Bootstrap作为前端展示框架。\r\n\r\nJeeSite **已内置** 一系列企业信息管理系统的基础功能，目前包括两大模块，系统管理（SYS）模块和内容管理（CMS）模块。系统管理模块，包括企业组织架构（用户管理、部门管理、区域管理）、菜单管理、角色权限管理、字典管理等功能；内容管理模块，包括内容管理（文章、链接），栏目管理、站点管理、公共留言、文件管理、前端网站展示等功能。\r\n\r\nJeeSite提供了常用工具进行封装，包括日志工具、缓存工具、服务器端验证、数据字典、当前组织机构数据（用户、区域、部门）以及其它常用小工具等。另外还提供一个基于本基础框架的 **代码生成器** ，为你生成基本模块代码，如果你使用了JeeSite基础框架，就可以很快速开发出优秀的信息管理系统。\r\n\r\n##为何选择\r\n\r\n1. 使用 **Apache License 2.0** 协议，源代码完全开源，无商业限制。\r\n2. 使用目前最主流的J2EE开发框架，简单易学，学习成本低。\r\n3. 数据库无限制，支持MySql、Oracle、SQL Server、H2等数据库。\r\n4. 模块化设计，层次结构清晰。内置一系列企业信息管理的基础功能。\r\n5. 权限控制精密细致，对所有管理链接都进行权限验证，可控制到按钮。\r\n6. 提供基本功能模块的源代码生成器，提高开发效率及质量。\r\n7. 提供常用工具类封装，日志、缓存、验证、字典、组织机构等，常用标签（taglib），获取当前组织机构、字典等数据。\r\n8. 完全兼容目前最流行浏览器（IE6、IE7+、Firefox、Chrome）。\r\n\r\n##使用技术\r\n\r\n1、Services相关\r\n\r\n* Core Framework：Spring Framework 3.1。\r\n* Security Framework：Apache Shiro 1.2。\r\n\r\n2、Web相关\r\n\r\n* MVC Framework：SpringMVC 3.1。\r\n* Layout Decoration：SiteMesh 2.4。\r\n* JavaScript Library：JQuery 1.7。\r\n* CSS Framework：Twitter Bootstrap 2.0.4。\r\n* JavaScript/CSS Compressor：YUI Compressor 2.4。\r\n* Front Validation：JQuery Validation Plugin 1.9。\r\n\r\n3、Database相关\r\n\r\n* ORM Framework：Spring-Data-JPA 1.2、Hibernate 4.1。\r\n* Connection Pool：BoneCP 0.7\r\n* Bean Validation：Hibernate Validation 4.3.0。\r\n* Cache：Ehcache 2.6。\r\n\r\n4、Tools 相关\r\n\r\n* Commons：Apache Commons\r\n* JSON Mapper：Jackson 2.1\r\n* Bean Mapper：Dozer 5.3.2\r\n* Full-text search：Hibernate Search 4.2（Apache Lucene 3.6）、IK Analyzer 2012_u6中文分词\r\n* Log Manager：Log4j 1.2\r\n\r\n##安全考虑\r\n\r\n1. 开发语言：系统采用Java 语言开发，具有卓越的通用性、高效性、平台移植性和安全性。\r\n2. 分层设计：（数据库层，数据访问层，业务逻辑层，展示层）层次清楚，低耦合，各层必须通过接口才能接入并进行参数校验（如：在展示层不可直接操作数据库），保证数据操作的安全。\r\n3. 双重验证：用户表单提交双验证：包括服务器端验证及客户端验证，防止用户通过浏览器恶意修改（如不可写文本域、隐藏变量篡改、上传非法文件等），跳过客户端验证操作数据库。\r\n4. 安全编码：用户表单提交所有数据，在服务器端都进行安全编码，防止用户提交非法脚本及SQL注入获取敏感数据等，确保数据安全。\r\n5. 密码加密：登录用户密码进行SHA1散列加密，此加密方法是不可逆的。保证密文泄露后的安全问题。\r\n6. 强制访问：系统对所有管理端链接都进行用户身份权限验证，防止用户\r\n\r\n##快速体验\r\n\r\n1. 具备运行环境：JDK1.6、Maven3.0、MySql。\r\n2. 修改src\\main\\resources\\application.properties文件中的数据库设置参数。\r\n3. 根据修改参数创建对应MySql数据库。\r\n4. 运行bin\\resresh-db\\refresh-db.bat脚本，导入表结构及演示数据\r\n5. 运行bin\\jetty.bat，启动服务器（第一次运行，需要下载依赖jar包，请耐心等待）。\r\n6. 最高管理员，用户名：thinkgem 密码：admin\r\n\r\n##更多文档\r\n\r\n* [JeeSite介绍演示.docx](http://126.am/JKweM1)\r\n* [JeeSite开发手册.docx](http://126.am/1BXNX1)\r\n\r\n## 交流、反馈、参与贡献？ \r\n\r\n* QQ群：127515876\r\n* E-mail：thinkgem@163.com\r\n* Github：[https://github.com/thinkgem/jeesite](http://126.am/lRXKx0)\r\n\r\n如果你想参与进来共同完善它或有更好的建议，请联系我吧(^_^)。\r\n\r\n## 未来开发计划\r\n\r\n* 代码生成器：自动建立表结构、生成的mvc中包括属性字段，哪些可作为查询条件等等。\r\n* 模块管理功能：可方便增减模块，如内容管理模块不需要，可直接启用或停用。\r\n* 内容管理模块：文章评论、完善内容关键字、图片模型、专题功能、会员功能。\r\n* 添加通用模块：通知通告功能、短信、邮件群发功能。\r\n* 嵌入流程引擎：使用Activit5或JBPM5流程引擎。\r\n* 公共工具封装：嵌入地图、生成报表、WebService\r\n* 移动客户端：暂定为Android客户端开发","google":"","note":"Don't delete this file! It's used internally to help with page regeneration."}